{
    "vix_last": 18.63,
    "vix_change": -0.86,
    "vix_5ma": 18.048,
    "vxtlt_last": 10.9,
    "vxtlt_change": 0.0,
    "cor1m_last": 10.44,
    "opex_date": "2026-07-17",
    "days_to_opex": 23,
    "opex_warning": false,
    "ratio_last": 1.3627,
    "ratio_20ma": 1.4029,
    "ratio_50ma": 1.4139,
    "xly_xlp_divergence": false,
    "xlk_breadth_last": 70.0,
    "xlk_breadth_change": 0.0,
    "xlf_breadth_last": 90.0,
    "xlf_breadth_change": 0.0,
    "xly_breadth_last": 60.0,
    "xly_breadth_change": 10.0,
    "sectors_today": {
        "XLK": -0.62,
        "XLF": -0.3,
        "XLY": 1.15,
        "XLE": -1.63,
        "XLV": 0.77,
        "XLP": 0.86,
        "XLU": 1.04,
        "XLB": 0.57,
        "XLI": 1.16,
        "XLRE": -0.29,
        "XLC": -0.68
    },
    "mcclellan_last": -0.0718,
    "net_advances_last": 0,
    "dist_to_pos50": 50.0718,
    "dist_to_neg50": -49.9282,
    "dist_to_pos100": 100.0718,
    "dist_to_neg100": -99.9282,
    "liquidity_last": 6400.0,
    "liquidity_change": 0.0,
    "liquidity_20ma": 6400.0,
    "liquidity_q10": 6400.0,
    "liquidity_q90": 6400.0,
    "oas_last": 3.5,
    "oas_20ma": 3.5,
    "dix_last": 0.407846,
    "dix_yesterday": 0.411072,
    "dix_change": -0.003226,
    "gex_last": 470387847.89,
    "institution_buy_signal": false
}